[
    {
        "Id":37,
        "Name":"Shirt",
        "Price":999,
        "Mrp":1199,
        "offers":50,
        "Type":"Cotton Shirt",
        "Category": "shirt",
        "Image":"./../src/assets/men_shirt_1.webp",
        "Quantity":1,
        "Offer":20,
        "Rating":3.5
    },
    {
        "Id":38,
        "Name":"Shirt",
        "Price":399,
        "Mrp":1199,
        "offers":50,
        "Type":"Cotton Shirt",
        "Category": "shirt",
        "Image":"./../src/assets/men_shirt_2.webp",
        "Quantity":1,
        "Offer":25,
        "Rating":2.7
    },
    {
        "Id":39,
        "Name":"T Shirt",
        "Price":449,
        "Mrp":1199,
        "offers":50,
        "Type":"T shirt",
        "Category": "t shirt",
        "Image":"./../src/assets/girl-blue1_1.webp",
        "Quantity":1,
        "Offer":20,
        "Rating":4.2
    },
    {
        "Id":40,
        "Name":"T Shirt",
        "Price":799,
        "Mrp":1199,
        "offers":50,
        "Type":"T shirt",
        "Category": "t shirt",
        "Image":"./../src/assets/girl-gray-1.webp",
        "Quantity":1,
        "Offer":50,
        "Rating":4.7
    },
     
    {
        "Id":41,
        "Name":"Hoodie",
        "Price":299,
        "Mrp":1199,
        "offers":50,
        "Type":"Hoodie",
        "Category": "hoodie",
        "Image":"./../src/assets/men_hoodie_1.1.webp",
        "Quantity":1,
        "Offer":30,
        "Rating":4.9
    },
    
    {
        "Id":42,
        "Name":"Hoodie",
        "Price":249,
        "Mrp":1199,
        "offers":50,
        "Type":"Cotton",
        "Category": "hoodie",
        "Image":"./../src/assets/girl_2.webp",
        "Quantity":1,
        "Offer":15,
        "Rating":2.4
    }
   
]